cachetools_async/__init__.py
cachetools_async/decorators.py
cachetools_async/py.typed
cachetools_async-0.0.5.dist-info/METADATA
cachetools_async-0.0.5.dist-info/WHEEL
cachetools_async-0.0.5.dist-info/licenses/LICENSE
cachetools_async-0.0.5.dist-info/RECORD
