Metadata-Version: 2.4
Name: cachetools-async
Version: 0.0.5
Summary: Provides decorators that are inspired by and work closely with cachetools' for caching asyncio functions and methods.
Project-URL: Repository, https://github.com/imnotjames/cachetools-async.git
Project-URL: Issues, https://github.com/imnotjames/cachetools-async/issues
Author-email: James Ward <james@notjam.es>
License-Expression: MIT
License-File: LICENSE
Requires-Python: >=3.9
Requires-Dist: cachetools>=5
